cloudshell/__init__.py
cloudshell/shell/__init__.py
cloudshell/shell/standards/__init__.py
cloudshell/shell/standards/attribute_names.py
cloudshell/shell/standards/autoload_generic_models.py
cloudshell/shell/standards/exceptions.py
cloudshell/shell/standards/resource_config_generic_models.py
cloudshell/shell/standards/core/__init__.py
cloudshell/shell/standards/core/namespace_type.py
cloudshell/shell/standards/core/utils.py
cloudshell/shell/standards/core/autoload/__init__.py
cloudshell/shell/standards/core/autoload/core_entities.py
cloudshell/shell/standards/core/autoload/existed_resource_info.py
cloudshell/shell/standards/core/autoload/resource_model.py
cloudshell/shell/standards/core/autoload/utils.py
cloudshell/shell/standards/core/resource_conf/__init__.py
cloudshell/shell/standards/core/resource_conf/attrs_converter.py
cloudshell/shell/standards/core/resource_conf/attrs_converters.py
cloudshell/shell/standards/core/resource_conf/attrs_getter.py
cloudshell/shell/standards/core/resource_conf/base_conf.py
cloudshell/shell/standards/core/resource_conf/enum.py
cloudshell/shell/standards/core/resource_conf/resource_attr.py
tests/__init__.py
tests/conftest.py
tests/cloudshell/__init__.py
tests/cloudshell/shell/__init__.py
tests/cloudshell/shell/standards/__init__.py
tests/cloudshell/shell/standards/test_resource_config_generic_models.py
tests/cloudshell/shell/standards/core/__init__.py
tests/cloudshell/shell/standards/core/test_utils.py
tests/cloudshell/shell/standards/core/resource_conf/__init__.py
tests/cloudshell/shell/standards/core/resource_conf/test_attrs_converters.py
tests/cloudshell/shell/standards/core/resource_conf/test_enum.py
tests/cloudshell/shell/standards/core/resource_conf/test_simple_conf.py
tests/cloudshell/shell_standards/__init__.py
tests/cloudshell/shell_standards/test_autoload_details_builder.py
tests/cloudshell/shell_standards/test_autoload_generic_models.py
cloudshell_shell_standards-2.0.4.dist-info/LICENSE.htm
cloudshell_shell_standards-2.0.4.dist-info/METADATA
cloudshell_shell_standards-2.0.4.dist-info/WHEEL
cloudshell_shell_standards-2.0.4.dist-info/top_level.txt
cloudshell_shell_standards-2.0.4.dist-info/RECORD
