Metadata-Version: 2.1
Name: cloudshell-shell-standards
Version: 2.0.4
Summary: QualiSystems Shells Standards Package
Home-page: http://www.qualisystems.com/
Author: Quali
Author-email: info@quali.com
Requires-Python: ~=3.7
License-File: LICENSE.htm
Requires-Dist: cloudshell-shell-core (<7,>=5)
Requires-Dist: cloudshell-automation-api (>=2021)
Requires-Dist: typing-extensions (>=4.0)
Requires-Dist: attrs (>=21)
